pyadverse/__init__.py
pyadverse/risk_metrics.py
pyadverse-0.0.3.dist-info/METADATA
pyadverse-0.0.3.dist-info/WHEEL
pyadverse-0.0.3.dist-info/top_level.txt
pyadverse-0.0.3.dist-info/RECORD
