Metadata-Version: 2.4
Name: pyadverse
Version: 0.0.3
Summary: Risk Metrics library for financial analysis
Author: Ajeet Rai
License: MIT
Classifier: License :: OSI Approved :: MIT License
Classifier: Programming Language :: Python :: 3
Requires-Dist: numpy
Dynamic: author
Dynamic: classifier
Dynamic: description
Dynamic: description-content-type
Dynamic: license
Dynamic: requires-dist
Dynamic: summary
